README.md
setup.py
agea_tools/__init__.py
agea_tools/config.py
agea_tools.egg-info/PKG-INFO
agea_tools.egg-info/SOURCES.txt
agea_tools.egg-info/dependency_links.txt
agea_tools.egg-info/requires.txt
agea_tools.egg-info/top_level.txt
agea_tools/navegacion/__init__.py
agea_tools/navegacion/conexiones.py
agea_tools/navegacion/helpers.py
agea_tools/navegacion/navegacion.py
agea_tools/navegacion/pases.py
agea_tools/navegacion/standardizing.py
agea_tools/notas/__init__.py
agea_tools/notas/tools.py