Metadata-Version: 2.1
Name: agea-tools
Version: 0.0.5
Summary: Paquete para manejar acciones comunes a la hora de utilizar datos.
Home-page: https://bitbucket.org/ageabigdata/agea_tools
Author: Agea Big Data
Author-email: bigdata@agea.com.ar
License: MIT
Platform: UNKNOWN
